pythoninfo/__init__.py
pythoninfo/__main__.py
pythoninfo/resources/__init__.py
pythoninfo/resources/index.html
pythoninfo-0.1.2.dist-info/LICENSE
pythoninfo-0.1.2.dist-info/METADATA
pythoninfo-0.1.2.dist-info/WHEEL
pythoninfo-0.1.2.dist-info/top_level.txt
pythoninfo-0.1.2.dist-info/RECORD
