Metadata-Version: 2.1
Name: pythoninfo
Version: 0.1.2
Summary: Just for fan - phpinfo in python =)
Author-email: Kirill Vercetti <office@kyzima-spb.com>
License: MIT License
Project-URL: Homepage, https://github.com/kyzima-spb/pythoninfo
Project-URL: Repository, https://github.com/kyzima-spb/pythoninfo.git
Requires-Python: >=3.6
License-File: LICENSE
Requires-Dist: importlib-metadata ; python_version < "3.8"
Requires-Dist: importlib-resources ; python_version < "3.9"
